app/__init__.py
app/dnd_firefly.py
dnd_firefly-0.4.1.dist-info/LICENSE
dnd_firefly-0.4.1.dist-info/METADATA
dnd_firefly-0.4.1.dist-info/WHEEL
dnd_firefly-0.4.1.dist-info/entry_points.txt
dnd_firefly-0.4.1.dist-info/top_level.txt
dnd_firefly-0.4.1.dist-info/RECORD
